mcp_server_things3/__init__.py
mcp_server_things3/applescript_handler.py
mcp_server_things3/config.py
mcp_server_things3/fast_server.py
mcp_server_things3/applescript/get_anytime_tasks.applescript
mcp_server_things3/applescript/get_inbox_tasks.applescript
mcp_server_things3/applescript/get_projects.applescript
mcp_server_things3/applescript/get_todays_tasks.applescript
mcp_server_things3/applescript/get_upcoming_tasks.applescript
mcp_server_things3/applescript/search_todos.applescript
things3_mcp-0.1.1.dist-info/METADATA
things3_mcp-0.1.1.dist-info/WHEEL
things3_mcp-0.1.1.dist-info/entry_points.txt
things3_mcp-0.1.1.dist-info/RECORD
