Metadata-Version: 2.4
Name: things3-mcp
Version: 0.1.1
Summary: A server implementation for interacting with Things3 app on macOS through Claude AI
Project-URL: Homepage, https://github.com/darinkishore/mcp-things3
Project-URL: Repository, https://github.com/darinkishore/mcp-things3
Project-URL: Issues, https://github.com/darinkishore/mcp-things3/issues
Author-email: Darin Kishore <darin@darinkishore.com>
License: MIT
Keywords: claude,macos,mcp,task-management,things3
Classifier: Development Status :: 4 - Beta
Classifier: Intended Audience :: Developers
Classifier: License :: OSI Approved :: MIT License
Classifier: Operating System :: MacOS
Classifier: Programming Language :: Python :: 3
Classifier: Programming Language :: Python :: 3.10
Classifier: Programming Language :: Python :: 3.11
Classifier: Programming Language :: Python :: 3.12
Classifier: Topic :: Office/Business :: Scheduling
Classifier: Topic :: Software Development :: Libraries :: Python Modules
Requires-Python: >=3.10
Requires-Dist: fastmcp>=0.1.0
Requires-Dist: mcp>=0.1.0
Requires-Dist: pydantic-settings>=2.0.0
